Workbook
Name _Año: #REF!
Name _Año: #REF!
Name _Año: #REF!
Name _DAT1: [1]EFINAN!$A$2:$A$2199
Name _DAT2: [1]EFINAN!$B$2:$B$2199
Name _DAT3: [1]EFINAN!$C$2:$C$2199
Name _UVT: #REF!
Name _UVT: #REF!
Name _UVT: #REF!
Name A_impresión_IM: [2]PYG0003!$A$8:$H$243
Name ABC: '[3]CENTROS DE COSTOS'!$A$2:$A$56
Name ANEXOS: #REF!
Name ANEXOS: #REF!
Name ANEXOS: #REF!
Name ANEXOS4: #REF!
Name ANEXOS4: #REF!
Name ANEXOS4: #REF!
Name BALANCE1: #REF!
Name BALANCE1: #REF!
Name BALANCE1: #REF!
Name Button_1: "ANEXOC2000_PARA_SOCIEDADES_Hoja1_Lista"
Name CC: [4]Hoja1!$A$2:$B$44
Name CCOSTO: [5]Hoja1!$A$2:$B$44
Name CENTRO_DE_COSTOS: '[6]CENTROS DE COSTOS'!$A$2:$A$56
Name CentrodeCostos_Descripcion: '[6]CENTROS DE COSTOS'!$A$2:$B$56
Name COD_REPRES: #N/A
Name conceptos: [7]conceptos!$A$1:$A$56
Name Contrapartidas: [8]CUENTAS!$A$37:$A$170
Name CUENTA: [6]CUENTAS!$A$2:$A$557
Name Cuentas_Descripcion: [6]CUENTAS!$A$2:$B$557
Name DDDDDDDDDDDD: '[8]CENTROS DE COSTOS'!$A$2:$A$33
Name Dependientes: #REF!
Name Dependientes: #REF!
Name Dependientes: #REF!
Name deptos: [9]dane!$A$1:$A$33
Name descripcion_uen: [8]UEN!$A$2:$A$6
Name DialogoOtros: "Dialog Frame 1"
Name EEEEEEEEEEEE: '[8]CENTROS DE COSTOS'!$A$2:$B$33
Name ESTADO: #REF!
Name ESTADO: #REF!
Name ESTADO: #REF!
Name i: [4]Hoja1!$A$2:$B$44
Name ibbgral: "Chart 19"
Name Mtrx_Conceptos: [8]CUENTAS!$A$2:$B$34
Name Mtrx_Contra: [8]CUENTAS!$A$37:$B$170
Name Mtrx_Proyectos: [8]PROYECTOS!$A$2:$B$29
Name muns: [9]dane!$B$1:$B$581
Name Nombre_CC: [10]Premisas2!$B$4:$B$57
Name NombreCC_y_Vice: [10]Premisas2!$B$4:$D$57
Name PLANTAAB2003: [11]Hoja1!$A$2:$B$44
Name Proyecto: [6]PROYECTOS!$A$2:$A$48
Name Proyecto_Descr: [6]PROYECTOS!$A$2:$B$48
Name Proyectos: [8]PROYECTOS!$A$2:$A$29
Name RTAPP: '[12]Renta Presuntiva'!$J$70
Name Saf: #REF!
Name Saf: #REF!
Name Saf: #REF!
Name SSS: #REF!
Name SSS: #REF!
Name SSS: #REF!

Sheet TARIFA ORDINARIO
C5: Valor UVT | F5: 34270
C6: Valor Renta Liquida Gravable (Rlg) | F6: =+EJERCICIO!G17 -> 38625000
C7: o Ganancia Ocasional Gravable | F7: =+ROUND(F6/F5,2) -> 1127.08
C9: Rangos en UVT
C10: Desde | D10: Hasta | E10: Tarifa marginal | F10: Impuesto
C11: 0 | D11: 1090 | E11: 0 | F11: 0
C12: 1090 | D12: 1700 | E12: 0.19 | F12: (RlgUVT-1090UVT)*19%
C13: 1700 | D13: 4100 | E13: 0.28 | F13: (RlgUVT-1700UVT)*28%+116UVT
C14: 4100 | D14: en adelante | E14: 0.33 | F14: (RlgUVT-4100UVT)*33%+788UVT | G14: =+ROUND(IF(F7>1090,IF(F7>1700,IF(F7>4100,(F7-4100)*33%+788,(F7-1700)*28%+116),(F7-1090)*19%),0),2) -> 7.05
C16: Valor Impuesto de Renta | F16: =+ROUND(G14*F5,-3) -> 242000
C17: o Impuesto de Ganancia Ocasional
C24: Valor UVT | F24: =+F5 -> 34270
C25: Valor Renta Liquida Gravable (Rlg) | F25: =+EJERCICIO!K17 -> 81900000
C26: o Ganancia Ocasional Gravable | F26: =+ROUND(F25/F24,2) -> 2389.85
C28: Rangos en UVT
C29: Desde | D29: Hasta | E29: Tarifa marginal | F29: Impuesto
C30: 0 | D30: 1090 | E30: 0 | F30: 0
C31: 1090 | D31: 1700 | E31: 0.19 | F31: (RlgUVT-1090UVT)*19%
C32: 1700 | D32: 4100 | E32: 0.28 | F32: (RlgUVT-1700UVT)*28%+116UVT
C33: 4100 | D33: en adelante | E33: 0.33 | F33: (RlgUVT-4100UVT)*33%+788UVT | G33: =+ROUND(IF(F26>1090,IF(F26>1700,IF(F26>4100,(F26-4100)*33%+788,(F26-1700)*28%+116),(F26-1090)*19%),0),2) -> 309.16
C35: Valor Impuesto de Renta | F35: =+ROUND(G33*F24,-3) -> 10595000
C36: o Impuesto de Ganancia Ocasional
C44: Valor UVT | F44: =+F24 -> 34270
C45: Valor Renta Liquida Gravable (Rlg) | F45: =+EJERCICIO!O17 -> 41900000
C46: o Ganancia Ocasional Gravable | F46: =+ROUND(F45/F44,2) -> 1222.64
C48: Rangos en UVT
C49: Desde | D49: Hasta | E49: Tarifa marginal | F49: Impuesto
C50: 0 | D50: 1090 | E50: 0 | F50: 0
C51: 1090 | D51: 1700 | E51: 0.19 | F51: (RlgUVT-1090UVT)*19%
C52: 1700 | D52: 4100 | E52: 0.28 | F52: (RlgUVT-1700UVT)*28%+116UVT | I52: NOTA: Para el año gravable 2019 la presente tabla NO está acutalizada; únicamente aplica hasta el segundo rango.
C53: 4100 | D53: en adelante | E53: 0.33 | F53: (RlgUVT-4100UVT)*33%+788UVT | G53: =+ROUND(IF(F46>1090,IF(F46>1700,IF(F46>4100,(F46-4100)*33%+788,(F46-1700)*28%+116),(F46-1090)*19%),0),2) -> 25.2
C55: Valor Impuesto de Renta | F55: =+ROUND(G53*F44,-3) -> 864000
C56: o Impuesto de Ganancia Ocasional

Sheet EJERCICIO
B2: EJERCICIO COMPARATIVO RENTAS DE TRABAJO
B4: "Gastos de representación - renta exenta numeral 7 artículo 206 E.T." | C4: 1 | D4: 1
B5: "Aportes voluntarios a pensión / cuentas AFC" | C5: 0
F7: CON LEY 1607 DE 2012 | J7: CON LEY 1819 DE 2016 | N7: CON LEY 1943 DE 2018
F8: DESCRIPCIÓN | G8: RENTA | J8: DESCRIPCIÓN | K8: RENTA | N8: DESCRIPCIÓN | O8: RENTA
F10: Ingresos laborales | G10: 150000000 | J10: Ingresos laborales | K10: =+G10 -> 150000000 | N10: Ingresos laborales | O10: =+K10 -> 150000000
J11: Ingresos no constitutivos de renta: | N11: Ingresos no constitutivos de renta:
F12: Aportes obligatorios salud | G12: =ROUND(+G10*0.04,-3) -> 6000000 | J12: Aportes obligatorios salud | K12: =+G12 -> 6000000 | N12: Aportes obligatorios salud | O12: =+K12 -> 6000000
F13: Aportes obligatorios pensión | G13: =ROUND(+G10*0.05,-3) -> 7500000 | J13: Aportes obligatorios pensión | K13: =+G13 -> 7500000 | N13: Aportes obligatorios pensión | O13: =+K13 -> 7500000
F14: Deducciones imputables (art. 387 del E.T., cesantías partícipe independiente y GMF) | G14: 45000000 | J14: Rentas exentas y deducciones imputables | K14: =+K29 -> 97875000 | N14: Rentas exentas y deducciones imputables | O14: =+O29 -> 97875000
F15: =IF(+D4,+B4,B5) -> "Gastos de representación - renta exenta numeral 7 artículo 206 E.T." | G15: 40000000 | J15: Rentas exentas y deducciones imputables (LIMITADAS) | K15: =+K39 -> 54600000 | N15: =+J15 -> Rentas exentas y deducciones imputables (LIMITADAS) | O15: =+O42 -> 94600000
F16: Renta exenta 25% | G16: =ROUND(IF((G10-SUM(G12:G15))*0.25>(34270*240*12),(34270*240*12),(G10-SUM(G12:G15))*0.25),-3) -> 12875000
F17: Renta Líquida | G17: =+G10-SUM(G12:G16) -> 38625000 | J17: Renta Líquida cedular | K17: =+K10-K12-K13-K15 -> 81900000 | N17: Renta Líquida cedular | O17: =+O10-O12-O13-O15 -> 41900000
F19: Valor impuesto | G19: =+'TARIFA ORDINARIO'!F16 -> 242000 | J19: Valor impuesto | K19: =+'TARIFA ORDINARIO'!F35 -> 10595000 | N19: Valor impuesto | O19: =+'TARIFA ORDINARIO'!F55 -> 864000
J23: Para determinar límite rentas exentas y deducciones: | N23: Para determinar límite rentas exentas y deducciones:
J25: Valores iniciales: | N25: Valores iniciales:
J26: Renta exenta del 25% | K26: =+G16 -> 12875000 | N26: Renta exenta del 25% | O26: =+K26 -> 12875000
J27: =+F15 -> "Gastos de representación - renta exenta numeral 7 artículo 206 E.T." | K27: =+G15 -> 40000000 | N27: =+J27 -> "Gastos de representación - renta exenta numeral 7 artículo 206 E.T." | O27: =+G15 -> 40000000
J28: Deducciones imputables | K28: =+G14 -> 45000000 | N28: Deducciones imputables | O28: =+K28 -> 45000000
K29: =SUM(K26:K28) -> 97875000 | O29: =SUM(O26:O28) -> 97875000
J30: Cálculo límite: | N30: Cálculo límite:
J32: Ingresos | K32: =+K10 -> 150000000 | N32: Ingresos | O32: =+O10 -> 150000000
J33: (-) ingresos no constitutivos de renta (salud y pensión) | K33: =-SUM(K12:K13) -> -13500000 | N33: (-) ingresos no constitutivos de renta (salud y pensión) | O33: =-SUM(O12:O13) -> -13500000
J34: Ingresos netos | K34: =SUM(K32:K33) -> 136500000 | N34: Ingresos netos | O34: =SUM(O32:O33) -> 136500000
J36: Límite inicial (40%) | K36: =ROUND(+K34*0.4,-3) -> 54600000 | N36: Límite inicial (40%) | O36: =ROUND(+O34*0.4,-3) -> 54600000
J37: Límite máximo no superior a 5.040 UVTs | K37: =ROUND(34270*5040,-3) -> 172721000 | N37: Límite máximo no superior a 5.040 UVTs | O37: =ROUND(34270*5040,-3) -> 172721000
J39: Monto máximo definitivo | K39: =IF(+K36>K37,K37,K36) -> 54600000 | N39: Monto máximo definitivo | O39: =IF(IF(+O36>O37,O37,O36)>+O26+O28,+O26+O28,IF(+O36>O37,O37,O36)) -> 54600000
N41: (+) rentas exentas no sometidas a límite | O41: =IF(D4=1,G15,0) -> 40000000
N42: Total rentas exentas y deducciones imputables (limitadas) | O42: =+O39+O41 -> 94600000
